confidentialmind_core/__init__.py
confidentialmind_core/config.py
confidentialmind_core/config_manager.py
confidentialmind_core/model_client.py
confidentialmind_core/usage_tracker.py
confidentialmind_core-0.1.18.dist-info/licenses/LICENSE
confidentialmind_core-0.1.18.dist-info/licenses/NOTICE
confidentialmind_core-0.1.18.dist-info/METADATA
confidentialmind_core-0.1.18.dist-info/WHEEL
confidentialmind_core-0.1.18.dist-info/top_level.txt
confidentialmind_core-0.1.18.dist-info/RECORD
