Metadata-Version: 2.4
Name: confidentialmind-core
Version: 0.1.18
Summary: Core functionality for interfacing with the ConfidentialMind stack
Author-email: confidentialmind <info@confidentialmind.com>
License: Apache-2.0
Project-URL: Homepage, https://www.confidentialmind.com/
Classifier: Programming Language :: Python :: 3
Classifier: License :: OSI Approved :: Apache Software License
Classifier: Operating System :: OS Independent
Requires-Python: >=3.10
License-File: LICENSE
License-File: NOTICE
Requires-Dist: pydantic<3.0.0,>=2.8.2
Requires-Dist: websockets>=12.0
Requires-Dist: python-dotenv
Requires-Dist: openai>=1.0.0
Requires-Dist: aiohttp>=3.8.0
Requires-Dist: aiofiles>=23.0.0
Requires-Dist: requests>=2
Dynamic: license-file
